{"cameraMode":{"drawMode":0,"name":"Shaded","section":"Shading Mode"},"sceneLighting":true,"audioPlay":false,"sceneViewState":{"m_AlwaysRefresh":false,"showFog":true,"showSkybox":true,"showFlares":true,"showImageEffects":true,"showParticleSystems":true,"showVisualEffectGraphs":true,"m_FxEnabled":true},"in2DMode":false,"pivot":{"x":27.95032501220703,"y":21.12863540649414,"z":29.802637100219728},"rotation":{"x":-0.12306959182024002,"y":0.7353762984275818,"z":-0.14717459678649903,"w":-0.6506556272506714},"size":1.0612510442733765,"orthographic":false}